net_and_server_utils/__init__.py
net_and_server_utils/cgi_interfacing.py
net_and_server_utils/handling_programs_remotely.py
net_and_server_utils/http_client_services.py
net_and_server_utils/ipaddress_handling.py
net_and_server_utils/socketserver_creation.py
net_and_server_utils/ssl_socket.py
net_and_server_utils-0.0.2.dist-info/METADATA
net_and_server_utils-0.0.2.dist-info/WHEEL
net_and_server_utils-0.0.2.dist-info/top_level.txt
net_and_server_utils-0.0.2.dist-info/RECORD
