Metadata-Version: 2.1
Name: net-and-server-utils
Version: 0.0.2
Summary: A package created for easy usage of network and server utils - XMLRPC Server and Client Creation,
Project-URL: Source, https://github.com/Yuvnish017/net_and_server_utils/tree/master
